{
  "$schema": "https://raw.githubusercontent.com/spdx/spdx-spec/v2.2.1/schemas/spdx-schema.json",
  "spdxVersion": "SPDX-2.2",
  "dataLicense": "CC0-1.0",
  "SPDXID": "SPDXRef-DOCUMENT",
  "documentNamespace": "https://spdx.org/spdxdocs/boost-winapi-x64-windows-1.87.0-2c21e924-5556-46dc-9051-54710e56601a",
  "name": "boost-winapi:x64-windows@1.87.0 2094dff95e90468cf6ffbb3a738f734eb41cd16c3da122aca1c975bdf623eab6",
  "creationInfo": {
    "creators": [
      "Tool: vcpkg-2024-12-09-1005b78fa1bf1dde1a20c2734cba4ea61ca94d9a"
    ],
    "created": "2025-03-25T11:49:53Z"
  },
  "relationships": [
    {
      "spdxElementId": "SPDXRef-port",
      "relationshipType": "GENERATES",
      "relatedSpdxElement": "SPDXRef-binary"
    },
    {
      "spdxElementId": "SPDXRef-port",
      "relationshipType": "CONTAINS",
      "relatedSpdxElement": "SPDXRef-file-0"
    },
    {
      "spdxElementId": "SPDXRef-port",
      "relationshipType": "CONTAINS",
      "relatedSpdxElement": "SPDXRef-file-1"
    },
    {
      "spdxElementId": "SPDXRef-binary",
      "relationshipType": "GENERATED_FROM",
      "relatedSpdxElement": "SPDXRef-port"
    },
    {
      "spdxElementId": "SPDXRef-file-0",
      "relationshipType": "CONTAINED_BY",
      "relatedSpdxElement": "SPDXRef-port"
    },
    {
      "spdxElementId": "SPDXRef-file-1",
      "relationshipType": "CONTAINED_BY",
      "relatedSpdxElement": "SPDXRef-port"
    }
  ],
  "packages": [
    {
      "name": "boost-winapi",
      "SPDXID": "SPDXRef-port",
      "versionInfo": "1.87.0",
      "downloadLocation": "git+https://github.com/microsoft/vcpkg@9c479ba00f4e2401e518595446748e4394cd9568",
      "homepage": "https://www.boost.org/libs/winapi",
      "licenseConcluded": "BSL-1.0",
      "licenseDeclared": "NOASSERTION",
      "copyrightText": "NOASSERTION",
      "description": "Boost winapi module",
      "comment": "This is the port (recipe) consumed by vcpkg."
    },
    {
      "name": "boost-winapi:x64-windows",
      "SPDXID": "SPDXRef-binary",
      "versionInfo": "2094dff95e90468cf6ffbb3a738f734eb41cd16c3da122aca1c975bdf623eab6",
      "downloadLocation": "NONE",
      "licenseConcluded": "BSL-1.0",
      "licenseDeclared": "NOASSERTION",
      "copyrightText": "NOASSERTION",
      "comment": "This is a binary package built by vcpkg."
    },
    {
      "SPDXID": "SPDXRef-resource-0",
      "name": "boostorg/winapi",
      "downloadLocation": "git+https://github.com/boostorg/winapi@boost-1.87.0",
      "licenseConcluded": "NOASSERTION",
      "licenseDeclared": "NOASSERTION",
      "copyrightText": "NOASSERTION",
      "checksums": [
        {
          "algorithm": "SHA512",
          "checksumValue": "95a2f7770444a12add8fe5ce575a80f7af7446f92fbf971017dac6285e2bca1a4947cf9bcdf3e750647ebe004cec43f173c3f05f7bf5cf8badc4d75802ce2eb6"
        }
      ]
    }
  ],
  "files": [
    {
      "fileName": "./C:/Users/User/AppData/Local/vcpkg/registries/git-trees/9c479ba00f4e2401e518595446748e4394cd9568/portfile.cmake",
      "SPDXID": "SPDXRef-file-0",
      "checksums": [
        {
          "algorithm": "SHA256",
          "checksumValue": "1207453bf486126f0ba97a815b450100caee49e209c21d63d9e71c92983c24a4"
        }
      ],
      "licenseConcluded": "NOASSERTION",
      "copyrightText": "NOASSERTION"
    },
    {
      "fileName": "./C:/Users/User/AppData/Local/vcpkg/registries/git-trees/9c479ba00f4e2401e518595446748e4394cd9568/vcpkg.json",
      "SPDXID": "SPDXRef-file-1",
      "checksums": [
        {
          "algorithm": "SHA256",
          "checksumValue": "350be70bcec9c0e621f7a1a0c0bbcaffeb004106402be9091a8639c80ad26ebf"
        }
      ],
      "licenseConcluded": "NOASSERTION",
      "copyrightText": "NOASSERTION"
    }
  ]
}
